{
  "lastUpdated": "2026-04-03T16:44:02.042Z",
  "nextUpdate": "2026-04-03T17:44:02.042Z",
  "totalCount": 100,
  "sourceStats": {
    "BBC Arabic": 1,
    "New York Times": 8,
    "AP News": 5,
    "NYT Business": 8,
    "Le Monde": 10,
    "BBC World": 6,
    "Financial Times": 2,
    "朝日新聞 (Asahi)": 5,
    "Washington Post": 2,
    "RFI": 4,
    "Tagesschau": 5,
    "The Hindu": 9,
    "Le Figaro": 4,
    "NYT Technology": 1,
    "BBC Business": 2,
    "Deutsche Welle DE": 2,
    "AFP": 1,
    "The Guardian": 3,
    "NHK World": 2,
    "Times of India": 2,
    "FAZ": 9,
    "Al Jazeera EN": 2,
    "Die Zeit": 1,
    "Süddeutsche Zeitung": 2,
    "NDTV": 2,
    "Der Spiegel": 2
  },
  "categoryStats": {
    "global": 36,
    "usa": 24,
    "china": 10,
    "bigtech": 10,
    "germany": 10,
    "asia": 10
  },
  "topicStats": {
    "general": 23,
    "politics": 17,
    "technology": 25,
    "military": 25,
    "economy": 6,
    "domestic": 1,
    "environment": 2,
    "society": 1
  }
}