{
  "lastUpdated": "2026-03-18T10:58:54.795Z",
  "nextUpdate": "2026-03-18T11:58:54.795Z",
  "totalCount": 100,
  "sourceStats": {
    "BBC Russian": 1,
    "Tagesschau": 9,
    "RFI": 8,
    "Le Monde": 10,
    "BBC Mundo": 2,
    "NHK World": 6,
    "Deutsche Welle EN": 2,
    "Deutsche Welle DE": 6,
    "New York Times": 2,
    "BBC中文": 2,
    "The Guardian": 5,
    "El País": 7,
    "FAZ": 6,
    "Die Zeit": 9,
    "NPR World": 2,
    "Le Figaro": 5,
    "NYT Business": 2,
    "NPR News": 4,
    "Der Spiegel": 3,
    "NHK Economy": 2,
    "France 24 EN": 2,
    "Al Jazeera EN": 1,
    "RFI中文": 3,
    "AP News": 1
  },
  "categoryStats": {
    "global": 39,
    "usa": 21,
    "asia": 10,
    "bigtech": 10,
    "germany": 10,
    "china": 10
  },
  "topicStats": {
    "general": 29,
    "politics": 16,
    "military": 20,
    "technology": 26,
    "society": 6,
    "economy": 3
  }
}